fuzzy_pandas/__init__.py
fuzzy_pandas/fuzzy_merge.py
fuzzy_pandas-0.1.dist-info/LICENSE
fuzzy_pandas-0.1.dist-info/METADATA
fuzzy_pandas-0.1.dist-info/WHEEL
fuzzy_pandas-0.1.dist-info/top_level.txt
fuzzy_pandas-0.1.dist-info/RECORD
