Metadata-Version: 2.1
Name: fuzzy-pandas
Version: 0.1
Summary: Fuzzy matching in pandas using csvmatch
Home-page: http://github.com/jsoma/fuzzy_pandas
Author: Jonathan Soma
Author-email: jonathan.soma@gmail.com
License: MIT
Keywords: fuzzy matching pandas
Platform: UNKNOWN
Classifier: Intended Audience :: Developers
Classifier: Intended Audience :: End Users/Desktop
Classifier: Intended Audience :: Science/Research
Classifier: Natural Language :: English
Classifier: Operating System :: OS Independent
Classifier: Programming Language :: Python :: 3.7
Classifier: Topic :: Scientific/Engineering :: Information Analysis
Classifier: Topic :: Utilities
Requires-Dist: pandas
Requires-Dist: csvmatch
